dify_rag/__init__.py
dify_rag/extractor/__init__.py
dify_rag/extractor/csv_extractor.py
dify_rag/extractor/emr/__init__.py
dify_rag/extractor/emr/admission_record_extractor.py
dify_rag/extractor/emr/base.py
dify_rag/extractor/emr/constants.py
dify_rag/extractor/emr/emr_helper.py
dify_rag/extractor/emr/surgery_consent_extractor.py
dify_rag/extractor/emr/talk_record_extractor.py
dify_rag/extractor/emr_extractor.py
dify_rag/extractor/epub_extractor.py
dify_rag/extractor/excel_extractor.py
dify_rag/extractor/extractor_base.py
dify_rag/extractor/html/__init__.py
dify_rag/extractor/html/constants.py
dify_rag/extractor/html/html_helper.py
dify_rag/extractor/html/html_table.py
dify_rag/extractor/html/html_text.py
dify_rag/extractor/html/readability/__init__.py
dify_rag/extractor/html/readability/browser.py
dify_rag/extractor/html/readability/cleaners.py
dify_rag/extractor/html/readability/compat/__init__.py
dify_rag/extractor/html/readability/compat/three.py
dify_rag/extractor/html/readability/compat/two.py
dify_rag/extractor/html/readability/debug.py
dify_rag/extractor/html/readability/encoding.py
dify_rag/extractor/html/readability/htmls.py
dify_rag/extractor/html/readability/readability.py
dify_rag/extractor/html_extractor.py
dify_rag/extractor/markdown_extractor.py
dify_rag/extractor/markdown_trans_extractor.py
dify_rag/extractor/pdf/__init__.py
dify_rag/extractor/pdf/constants.py
dify_rag/extractor/pdf/pdf_helper.py
dify_rag/extractor/pdf/toc.py
dify_rag/extractor/pdf_extractor.py
dify_rag/extractor/utils.py
dify_rag/extractor/word_extractor.py
dify_rag/helper/__init__.py
dify_rag/helper/knowledge_api_base.py
dify_rag/models/__init__.py
dify_rag/models/constants.py
dify_rag/models/document.py
dify_rag/retrieval/__init__.py
dify_rag/retrieval/base.py
dify_rag/retrieval/post/__init__.py
dify_rag/retrieval/post/normal.py
dify_rag/retrieval/post/title_structrue.py
dify_rag/retrieval/pre/__init__.py
dify_rag/retrieval/schemas.py
dify_rag/retrieval/strategy.py
dify_rag-0.2.2.dist-info/METADATA
dify_rag-0.2.2.dist-info/WHEEL
dify_rag-0.2.2.dist-info/RECORD
