Metadata-Version: 2.1
Name: dify-rag
Version: 0.2.2
Summary: dify's rag patch module
Home-page: https://github.com/hustyichi/dify-rag
Author: yichi
Author-email: hustyichi@163.com
Requires-Python: >=3.9,<4.0
Classifier: Programming Language :: Python :: 3
Classifier: Programming Language :: Python :: 3.9
Classifier: Programming Language :: Python :: 3.10
Classifier: Programming Language :: Python :: 3.11
Classifier: Programming Language :: Python :: 3.12
Classifier: Programming Language :: Python :: 3.13
Requires-Dist: annotated-types (>=0.7.0,<0.8.0)
Requires-Dist: beautifulsoup4 (>=4.12.2,<5.0.0)
Requires-Dist: chardet (>=5.1.0,<6.0.0)
Requires-Dist: jieba (>=0.42.1,<0.43.0)
Requires-Dist: lxml-html-clean (>=0.2.0,<0.3.0)
Requires-Dist: markdown2 (>=2.5.2,<3.0.0)
Requires-Dist: numpy (>=1.26.4,<2.0.0)
Requires-Dist: openpyxl (>=3.1.5,<4.0.0)
Requires-Dist: pandas (>=2.2.2,<3.0.0)
Requires-Dist: pydantic (>=2.8.2,<3.0.0)
Requires-Dist: pydantic-core (>=2.20.1,<3.0.0)
Requires-Dist: pymupdf (>=1.24.9,<2.0.0)
Requires-Dist: pypandoc-binary (>=1.15,<2.0)
Requires-Dist: requests (>=2.30.0,<3.0.0)
Project-URL: Repository, https://github.com/hustyichi/dify-rag
